{
  "main": {
    "id": "9bbf06e4cfbe67b8",
    "type": "split",
    "children": [
      {
        "id": "c97c2dfacba948a0",
        "type": "tabs",
        "children": [
          {
            "id": "d15c616c8fd524ef",
            "type": "leaf",
            "state": {
              "type": "markdown",
              "state": {
                "file": "Reading Things to Look Into.md",
                "mode": "source",
                "source": false,
                "backlinks": false
              },
              "icon": "lucide-file",
              "title": "Reading Things to Look Into"
            }
          },
          {
            "id": "ec221ccc40ad4a8a",
            "type": "leaf",
            "state": {
              "type": "markdown",
              "state": {
                "file": "templates/Main Note.md",
                "mode": "source",
                "source": false,
                "backlinks": false
              },
              "icon": "lucide-file",
              "title": "Main Note"
            }
          }
        ],
        "currentTab": 1
      }
    ],
    "direction": "vertical"
  },
  "left": {
    "id": "852c94df77ef01f8",
    "type": "split",
    "children": [
      {
        "id": "ff6fd9cc28b25bf7",
        "type": "tabs",
        "children": [
          {
            "id": "bef70e8d3fd0d835",
            "type": "leaf",
            "state": {
              "type": "file-explorer",
              "state": {
                "sortOrder": "alphabetical",
                "autoReveal": false
              },
              "icon": "lucide-folder-closed",
              "title": "Files"
            }
          }
        ]
      }
    ],
    "direction": "horizontal",
    "width": 200
  },
  "right": {
    "id": "ea9dc36063e30de1",
    "type": "split",
    "children": [
      {
        "id": "8355b2072867512d",
        "type": "tabs",
        "children": [
          {
            "id": "88fa426244b1c2ac",
            "type": "leaf",
            "state": {
              "type": "tag",
              "state": {
                "sortOrder": "frequency",
                "useHierarchy": true
              },
              "icon": "lucide-tags",
              "title": "Tags"
            }
          },
          {
            "id": "15bf3c587e00d71d",
            "type": "leaf",
            "state": {
              "type": "git-history-view",
              "state": {},
              "icon": "lucide-file",
              "title": "Plugin no longer active"
            }
          },
          {
            "id": "4088d649c8982a3e",
            "type": "leaf",
            "state": {
              "type": "all-properties",
              "state": {
                "sortOrder": "frequency",
                "showSearch": false,
                "searchQuery": ""
              },
              "icon": "lucide-archive",
              "title": "All properties"
            }
          },
          {
            "id": "f58e3e63b8c2973a",
            "type": "leaf",
            "state": {
              "type": "backlink",
              "state": {
                "file": "remote/10 - Tags/agony.md",
                "collapseAll": false,
                "extraContext": false,
                "sortOrder": "alphabetical",
                "showSearch": false,
                "searchQuery": "",
                "backlinkCollapsed": false,
                "unlinkedCollapsed": true
              },
              "icon": "links-coming-in",
              "title": "Backlinks for agony"
            }
          },
          {
            "id": "506ec63cf50195a0",
            "type": "leaf",
            "state": {
              "type": "outgoing-link",
              "state": {
                "file": "remote/10 - Tags/agony.md",
                "linksCollapsed": false,
                "unlinkedCollapsed": true
              },
              "icon": "links-going-out",
              "title": "Outgoing links from agony"
            }
          },
          {
            "id": "b6ffd72b5e08eb88",
            "type": "leaf",
            "state": {
              "type": "outline",
              "state": {
                "file": "remote/Untitled Kanban.md"
              },
              "icon": "lucide-list",
              "title": "Outline of Untitled Kanban"
            }
          },
          {
            "id": "8ce620cb88e3c465",
            "type": "leaf",
            "state": {
              "type": "git-view",
              "state": {},
              "icon": "lucide-file",
              "title": "Plugin no longer active"
            }
          }
        ],
        "currentTab": 6
      }
    ],
    "direction": "horizontal",
    "width": 264.5,
    "collapsed": true
  },
  "left-ribbon": {
    "hiddenItems": {
      "workspaces:Manage workspace layouts": false,
      "templater-obsidian:Templater": false,
      "daily-notes:Open today's daily note": false,
      "templates:Insert template": false,
      "graph:Open graph view": false,
      "audio-recorder:Start/stop recording": false,
      "switcher:Open quick switcher": true,
      "command-palette:Open command palette": true,
      "markdown-importer:Open format converter": false,
      "zk-prefixer:Create new unique note": true,
      "omnisearch:Omnisearch": false,
      "obsidian-kanban:Create new board": false
    }
  },
  "active": "ec221ccc40ad4a8a",
  "lastOpenFiles": [
    "projects/belles-crafts Kanban.md",
    "projects/Belle's Crafts Brainstorming.md",
    "programming/div id=name-field class=form-item fields name required.md",
    "programming/def read_input().md",
    "programming/C++ Learning Notes.md",
    "programming/Arch Install (UEFI).md",
    "programming",
    "projects/Korg Triton Parts List.md",
    "projects/Korg Triton Parts List 1.md",
    "projects/AirPods Pro style earbuds with the option for an mmcx cable at the….md",
    "projects",
    "Programming/div id=name-field class=form-item fields name required.md",
    "Programming/def read_input().md",
    "Programming/C++ Learning Notes.md",
    "Programming/Arch Install (UEFI).md",
    "Programming",
    "Projects/Korg Triton Parts List.md",
    "Projects/Korg Triton Parts List 1.md",
    "Projects/AirPods Pro style earbuds with the option for an mmcx cable at the….md",
    "Projects",
    "rough-notes/Ideas/song idea 2-25-25.md",
    "source-material/Others/deadmau5 Masterclass notes.md",
    "rough-notes/Useful/Purchase dates for music gear.md",
    "rough-notes/Purchase dates for music gear.md",
    "03/07",
    "03",
    "hello.md",
    "1741399451-hello.md",
    "dailies/070320251946.md",
    "dailies/2025-03-07.md",
    "2025-03-07.md",
    "1741396309-USYQ.md",
    "dailies",
    "rough-notes/Useful",
    "rough-notes/Important",
    "mini-essays",
    "source-material/Others/Screenshot 2024-12-30 at 18.18.09.jpeg",
    "source-material/Sermons/Handwritten Notes/Drawing 9.png",
    "source-material/Sermons/Handwritten Notes/Drawing 13.png",
    "source-material/Sermons/Handwritten Notes/Drawing 7.png",
    "source-material/Sermons/Handwritten Notes/Drawing 12.png",
    "source-material/Sermons/Handwritten Notes/Drawing 15.png",
    "source-material/Sermons/Handwritten Notes/Drawing 11.png",
    "source-material/Sermons/Handwritten Notes/Drawing 14.png",
    "source-material/Sermons/Handwritten Notes/Drawing 10.png",
    "rough-notes/Ideas/Drawing 5.png",
    "remote/2 - Rough Notes/Projects/Project Planning.canvas",
    "remote/5 - Main Notes/Catholicism Research.canvas",
    "remote/Projects 1/Project Planning.canvas",
    "Project Planning.canvas"
  ]
}